[{"__symbolic":"module","version":3,"metadata":{"BaseChartDirective":{"__symbolic":"class","decorators":[{"__symbolic":"call","expression":{"__symbolic":"reference","module":"@angular/core","name":"Directive"},"arguments":[{"selector":"canvas[baseChart]","exportAs":"base-chart"}]}],"members":{"data":[{"__symbolic":"property","decorators":[{"__symbolic":"call","expression":{"__symbolic":"reference","module":"@angular/core","name":"Input"}}]}],"datasets":[{"__symbolic":"property","decorators":[{"__symbolic":"call","expression":{"__symbolic":"reference","module":"@angular/core","name":"Input"}}]}],"labels":[{"__symbolic":"property","decorators":[{"__symbolic":"call","expression":{"__symbolic":"reference","module":"@angular/core","name":"Input"}}]}],"options":[{"__symbolic":"property","decorators":[{"__symbolic":"call","expression":{"__symbolic":"reference","module":"@angular/core","name":"Input"}}]}],"chartType":[{"__symbolic":"property","decorators":[{"__symbolic":"call","expression":{"__symbolic":"reference","module":"@angular/core","name":"Input"}}]}],"colors":[{"__symbolic":"property","decorators":[{"__symbolic":"call","expression":{"__symbolic":"reference","module":"@angular/core","name":"Input"}}]}],"legend":[{"__symbolic":"property","decorators":[{"__symbolic":"call","expression":{"__symbolic":"reference","module":"@angular/core","name":"Input"}}]}],"chartClick":[{"__symbolic":"property","decorators":[{"__symbolic":"call","expression":{"__symbolic":"reference","module":"@angular/core","name":"Output"}}]}],"chartHover":[{"__symbolic":"property","decorators":[{"__symbolic":"call","expression":{"__symbolic":"reference","module":"@angular/core","name":"Output"}}]}],"__ctor__":[{"__symbolic":"constructor","parameters":[{"__symbolic":"reference","module":"@angular/core","name":"ElementRef"}]}],"ngOnInit":[{"__symbolic":"method"}],"ngOnChanges":[{"__symbolic":"method"}],"ngOnDestroy":[{"__symbolic":"method"}],"getChartBuilder":[{"__symbolic":"method"}],"updateChartData":[{"__symbolic":"method"}],"getDatasets":[{"__symbolic":"method"}],"refresh":[{"__symbolic":"method"}]},"statics":{"defaultColors":[[255,99,132],[54,162,235],[255,206,86],[231,233,237],[75,192,192],[151,187,205],[220,220,220],[247,70,74],[70,191,189],[253,180,92],[148,159,177],[77,83,96]]}},"ChartsModule":{"__symbolic":"class","decorators":[{"__symbolic":"call","expression":{"__symbolic":"reference","module":"@angular/core","name":"NgModule"},"arguments":[{"declarations":[{"__symbolic":"reference","name":"BaseChartDirective"}],"exports":[{"__symbolic":"reference","name":"BaseChartDirective"}],"imports":[]}]}]}}},{"__symbolic":"module","version":1,"metadata":{"BaseChartDirective":{"__symbolic":"class","decorators":[{"__symbolic":"call","expression":{"__symbolic":"reference","module":"@angular/core","name":"Directive"},"arguments":[{"selector":"canvas[baseChart]","exportAs":"base-chart"}]}],"members":{"data":[{"__symbolic":"property","decorators":[{"__symbolic":"call","expression":{"__symbolic":"reference","module":"@angular/core","name":"Input"}}]}],"datasets":[{"__symbolic":"property","decorators":[{"__symbolic":"call","expression":{"__symbolic":"reference","module":"@angular/core","name":"Input"}}]}],"labels":[{"__symbolic":"property","decorators":[{"__symbolic":"call","expression":{"__symbolic":"reference","module":"@angular/core","name":"Input"}}]}],"options":[{"__symbolic":"property","decorators":[{"__symbolic":"call","expression":{"__symbolic":"reference","module":"@angular/core","name":"Input"}}]}],"chartType":[{"__symbolic":"property","decorators":[{"__symbolic":"call","expression":{"__symbolic":"reference","module":"@angular/core","name":"Input"}}]}],"colors":[{"__symbolic":"property","decorators":[{"__symbolic":"call","expression":{"__symbolic":"reference","module":"@angular/core","name":"Input"}}]}],"legend":[{"__symbolic":"property","decorators":[{"__symbolic":"call","expression":{"__symbolic":"reference","module":"@angular/core","name":"Input"}}]}],"chartClick":[{"__symbolic":"property","decorators":[{"__symbolic":"call","expression":{"__symbolic":"reference","module":"@angular/core","name":"Output"}}]}],"chartHover":[{"__symbolic":"property","decorators":[{"__symbolic":"call","expression":{"__symbolic":"reference","module":"@angular/core","name":"Output"}}]}],"__ctor__":[{"__symbolic":"constructor","parameters":[{"__symbolic":"reference","module":"@angular/core","name":"ElementRef"}]}],"ngOnInit":[{"__symbolic":"method"}],"ngOnChanges":[{"__symbolic":"method"}],"ngOnDestroy":[{"__symbolic":"method"}],"getChartBuilder":[{"__symbolic":"method"}],"updateChartData":[{"__symbolic":"method"}],"getDatasets":[{"__symbolic":"method"}],"refresh":[{"__symbolic":"method"}]},"statics":{"defaultColors":[[255,99,132],[54,162,235],[255,206,86],[231,233,237],[75,192,192],[151,187,205],[220,220,220],[247,70,74],[70,191,189],[253,180,92],[148,159,177],[77,83,96]]}},"ChartsModule":{"__symbolic":"class","decorators":[{"__symbolic":"call","expression":{"__symbolic":"reference","module":"@angular/core","name":"NgModule"},"arguments":[{"declarations":[{"__symbolic":"reference","name":"BaseChartDirective"}],"exports":[{"__symbolic":"reference","name":"BaseChartDirective"}],"imports":[]}]}]}}}]